agentk8s/__init__.py
agentk8s/constant.py
agentk8s/main.py
agentk8s/openai.py
agentk8s-0.1.12.dist-info/METADATA
agentk8s-0.1.12.dist-info/WHEEL
agentk8s-0.1.12.dist-info/entry_points.txt
agentk8s-0.1.12.dist-info/RECORD
