Metadata-Version: 2.1
Name: agentk8s
Version: 0.1.12
Summary: k8s agent that does all the work for you.
Author: Saerdna
Author-email: 18320122+incomingflyingbrick@users.noreply.github.com
Requires-Python: >=3.8,<3.12
Classifier: Programming Language :: Python :: 3
Classifier: Programming Language :: Python :: 3.8
Classifier: Programming Language :: Python :: 3.9
Classifier: Programming Language :: Python :: 3.10
Classifier: Programming Language :: Python :: 3.11
Requires-Dist: docker (>=7.0.0,<8.0.0)
Requires-Dist: pyautogen[retrievechat] (>=0.2.2,<0.3.0)
Requires-Dist: socksio (>=1.0.0,<2.0.0)
Requires-Dist: typer[all] (>=0.9.0,<0.10.0)
